py_schwab_wrapper/__init__.py
py_schwab_wrapper/schwab_api.py
py_schwab_wrapper/utils/__init__.py
py_schwab_wrapper/utils/parameter_utils.py
py_schwab_wrapper-0.3.0.dist-info/LICENSE
py_schwab_wrapper-0.3.0.dist-info/METADATA
py_schwab_wrapper-0.3.0.dist-info/WHEEL
py_schwab_wrapper-0.3.0.dist-info/top_level.txt
py_schwab_wrapper-0.3.0.dist-info/RECORD
