Metadata-Version: 2.1
Name: py-schwab-wrapper
Version: 0.3.0
Summary: A Python wrapper for Schwab API
Home-page: https://github.com/CodeAndCandlesticks/py-schwab-wrapper
Author: Luis Perez
Author-email: luispe@gmail.com
License: UNKNOWN
Platform: UNKNOWN
Classifier: Programming Language :: Python :: 3
Classifier: License :: OSI Approved :: MIT License
Classifier: Operating System :: OS Independent
Requires-Python: >=3.6
License-File: LICENSE
Requires-Dist: flask
Requires-Dist: python-dotenv
Requires-Dist: pytz
Requires-Dist: requests
Requires-Dist: requests-oauthlib
